CHANGELOG.md
CMakeLists.txt
LICENSE
LICENSE_COSMICEMU
MANIFEST.in
README.md
pyproject.toml
setup.py
.github/environment.yml
.github/workflows/ci.yml
.github/workflows/publish.yml
benchmarks/ccl_test.c
benchmarks/ccl_test_f2d.c
benchmarks/ccl_test_f3d.c
benchmarks/ccl_test_utils.c
benchmarks/conftest.py
benchmarks/ctest.h
benchmarks/high_prec_pk_benchmarks.ipynb
benchmarks/test_baccoemu_baryons.py
benchmarks/test_baccoemu_linear.py
benchmarks/test_baccoemu_nonlinear.py
benchmarks/test_bbks.py
benchmarks/test_bcm.py
benchmarks/test_bocquet20_hmf.py
benchmarks/test_camb_class_consistent.py
benchmarks/test_cells.py
benchmarks/test_cib.py
benchmarks/test_concentration_Ishiyama21.py
benchmarks/test_correlation.py
benchmarks/test_correlation_3d.py
benchmarks/test_correlation_3drsd.py
benchmarks/test_correlation_MG.py
benchmarks/test_correlation_MG2.py
benchmarks/test_correlation_MG3_SD.py
benchmarks/test_cosmicemu.py
benchmarks/test_covariances.py
benchmarks/test_distances.py
benchmarks/test_eh.py
benchmarks/test_growth.py
benchmarks/test_halomod.py
benchmarks/test_halomod_numbercounts.py
benchmarks/test_haloprofile.py
benchmarks/test_hbf.py
benchmarks/test_hmf.py
benchmarks/test_hod.py
benchmarks/test_ia_profile.py
benchmarks/test_isw.py
benchmarks/test_kNL.py
benchmarks/test_massdef.py
benchmarks/test_nishimichi19_hmf.py
benchmarks/test_nonlimber.py
benchmarks/test_pk_4pt.py
benchmarks/test_power_mg.py
benchmarks/test_power_mg2.py
benchmarks/test_power_nu.py
benchmarks/test_ptpk.py
benchmarks/test_ptpk_bacco_lbias.py
benchmarks/test_ptpk_lpt.py
benchmarks/test_sigmaM.py
benchmarks/test_sz.py
benchmarks/test_timing.py
benchmarks/test_tracers.py
benchmarks/data/IA_halomodel_Cell_test.txt
benchmarks/data/IA_halomodel_norm_term.dat
benchmarks/data/Uchuu_m200-c200.crs.all
benchmarks/data/Uchuu_m200-c200.crs.relaxed
benchmarks/data/Uchuu_m200-c200.cvmax.all
benchmarks/data/Uchuu_m200-c200.cvmax.relaxed
benchmarks/data/Uchuu_m500-c500.crs.all
pyccl.egg-info/PKG-INFO
pyccl.egg-info/SOURCES.txt
pyccl.egg-info/dependency_links.txt
pyccl.egg-info/requires.txt
pyccl.egg-info/top_level.txt
