Metadata-Version: 2.2
Name: pyccl
Version: 3.2
Summary: Library of validated cosmological functions.
Author: LSST DESC
License: BSD
Project-URL: homepage, https://lsstdesc.org/
Project-URL: documentation, https://ccl.readthedocs.io/en/latest/
Project-URL: repository, https://github.com/LSSTDESC/CCL
Keywords: cosmology,astrophysics,physics,science,LSST
Classifier: Development Status :: 5 - Production/Stable
Classifier: Intended Audience :: Science/Research
Classifier: License :: OSI Approved :: BSD License
Classifier: Operating System :: MacOS :: MacOS X
Classifier: Operating System :: POSIX :: Linux
Classifier: Programming Language :: C
Classifier: Programming Language :: Python :: 3
Classifier: Topic :: Scientific/Engineering :: Astronomy
Classifier: Topic :: Scientific/Engineering :: Physics
Requires-Python: >=3.8
License-File: LICENSE
License-File: LICENSE_COSMICEMU
Requires-Dist: numpy<2
Provides-Extra: dev
Requires-Dist: pytest; extra == "dev"
Requires-Dist: pytest-cov; extra == "dev"
